<?xml version="1.0" encoding="UTF-8"?>
<DEFECTS>
  <DEFECT>
    <SFA>
      <FILEPATH>D:\Ark engine\Quake\</FILEPATH>
      <FILENAME>view.c</FILENAME>
      <LINE>118</LINE>
      <COLUMN>51</COLUMN>
    </SFA>
    <DEFECTCODE>26451</DEFECTCODE>
    <DESCRIPTION>Arithmetic overflow: Using operator '*' on a 4 byte value and then casting the result to a 8 byte value. Cast the value to the wider type before calling operator '*' to avoid overflow (io.2).</DESCRIPTION>
    <FUNCTION>V_CalcBob</FUNCTION>
    <DECORATED>V_CalcBob</DECORATED>
    <FUNCLINE>110</FUNCLINE>
    <PATH></PATH>
  </DEFECT>
  <DEFECT>
    <SFA>
      <FILEPATH>D:\Ark engine\Quake\</FILEPATH>
      <FILENAME>view.c</FILENAME>
      <LINE>123</LINE>
      <COLUMN>28</COLUMN>
    </SFA>
    <DEFECTCODE>26451</DEFECTCODE>
    <DESCRIPTION>Arithmetic overflow: Using operator '-' on a 4 byte value and then casting the result to a 8 byte value. Cast the value to the wider type before calling operator '-' to avoid overflow (io.2).</DESCRIPTION>
    <FUNCTION>V_CalcBob</FUNCTION>
    <DECORATED>V_CalcBob</DECORATED>
    <FUNCLINE>110</FUNCLINE>
    <PATH></PATH>
  </DEFECT>
  <DEFECT>
    <SFA>
      <FILEPATH>D:\Ark engine\Quake\</FILEPATH>
      <FILENAME>view.c</FILENAME>
      <LINE>128</LINE>
      <COLUMN>42</COLUMN>
    </SFA>
    <DEFECTCODE>26451</DEFECTCODE>
    <DESCRIPTION>Arithmetic overflow: Using operator '+' on a 4 byte value and then casting the result to a 8 byte value. Cast the value to the wider type before calling operator '+' to avoid overflow (io.2).</DESCRIPTION>
    <FUNCTION>V_CalcBob</FUNCTION>
    <DECORATED>V_CalcBob</DECORATED>
    <FUNCLINE>110</FUNCLINE>
    <PATH></PATH>
  </DEFECT>
  <DEFECT>
    <SFA>
      <FILEPATH>D:\Ark engine\Quake\</FILEPATH>
      <FILENAME>view.c</FILENAME>
      <LINE>128</LINE>
      <COLUMN>26</COLUMN>
    </SFA>
    <DEFECTCODE>26451</DEFECTCODE>
    <DESCRIPTION>Arithmetic overflow: Using operator '*' on a 4 byte value and then casting the result to a 8 byte value. Cast the value to the wider type before calling operator '*' to avoid overflow (io.2).</DESCRIPTION>
    <FUNCTION>V_CalcBob</FUNCTION>
    <DECORATED>V_CalcBob</DECORATED>
    <FUNCLINE>110</FUNCLINE>
    <PATH></PATH>
  </DEFECT>
  <DEFECT>
    <SFA>
      <FILEPATH>D:\Ark engine\Quake\</FILEPATH>
      <FILENAME>view.c</FILENAME>
      <LINE>459</LINE>
      <COLUMN>31</COLUMN>
    </SFA>
    <DEFECTCODE>26451</DEFECTCODE>
    <DESCRIPTION>Arithmetic overflow: Using operator '*' on a 4 byte value and then casting the result to a 8 byte value. Cast the value to the wider type before calling operator '*' to avoid overflow (io.2).</DESCRIPTION>
    <FUNCTION>V_CalcBlend</FUNCTION>
    <DECORATED>V_CalcBlend</DECORATED>
    <FUNCLINE>433</FUNCLINE>
    <PATH></PATH>
  </DEFECT>
  <DEFECT>
    <SFA>
      <FILEPATH>D:\Ark engine\Quake\</FILEPATH>
      <FILENAME>view.c</FILENAME>
      <LINE>804</LINE>
      <COLUMN>31</COLUMN>
    </SFA>
    <DEFECTCODE>26451</DEFECTCODE>
    <DESCRIPTION>Arithmetic overflow: Using operator '*' on a 4 byte value and then casting the result to a 8 byte value. Cast the value to the wider type before calling operator '*' to avoid overflow (io.2).</DESCRIPTION>
    <FUNCTION>V_CalcRefdef</FUNCTION>
    <DECORATED>V_CalcRefdef</DECORATED>
    <FUNCLINE>741</FUNCLINE>
    <PATH></PATH>
  </DEFECT>
</DEFECTS>